shrine/__init__.py
shrine/__version__.py
shrine/api_client.py
shrine/configuration.py
shrine/exceptions.py
shrine/rest.py
shrine/api/__init__.py
shrine/api/application_metadata_api.py
shrine/api/licences_api.py
shrine/api/policies_api.py
shrine/api/roles_api.py
shrine/models/__init__.py
shrine/models/access_controlled_action.py
shrine/models/access_controlled_resource.py
shrine/models/action_id.py
shrine/models/as_at_predicate_contract.py
shrine/models/as_at_range_for_spec.py
shrine/models/as_at_relative.py
shrine/models/attached_policy_definition_response.py
shrine/models/date_quality.py
shrine/models/date_unit.py
shrine/models/effective_date_has_quality.py
shrine/models/effective_date_relative.py
shrine/models/effective_range.py
shrine/models/entitlement_metadata.py
shrine/models/evaluation_request.py
shrine/models/evaluation_response.py
shrine/models/evaluation_result.py
shrine/models/for_spec.py
shrine/models/grant.py
shrine/models/how_spec.py
shrine/models/id_selector_definition.py
shrine/models/identifier_part_schema.py
shrine/models/if_expression.py
shrine/models/if_identity_claim_expression.py
shrine/models/if_identity_scope_expression.py
shrine/models/if_request_header_expression.py
shrine/models/key_value_pair_of_string_to_string.py
shrine/models/licence_creation_request.py
shrine/models/licence_selector_definition.py
shrine/models/licence_update_request.py
shrine/models/link.py
shrine/models/match_all_selector_definition.py
shrine/models/metadata_expression.py
shrine/models/metadata_selector_definition.py
shrine/models/non_transitive_supervisor_role_resource.py
shrine/models/operator.py
shrine/models/point_in_time_specification.py
shrine/models/policy_collection_creation_request.py
shrine/models/policy_collection_id.py
shrine/models/policy_collection_response.py
shrine/models/policy_collection_update_request.py
shrine/models/policy_creation_request.py
shrine/models/policy_id.py
shrine/models/policy_id_role_resource.py
shrine/models/policy_response.py
shrine_sdk-0.0.612.dist-info/METADATA
shrine_sdk-0.0.612.dist-info/WHEEL
shrine_sdk-0.0.612.dist-info/top_level.txt
shrine_sdk-0.0.612.dist-info/RECORD
