Metadata-Version: 2.1
Name: shrine-sdk
Version: 0.0.612
Summary: Python SDK for Shrine API
Home-page: https://github.com/finbourne/shrine-sdk-python
Author: FINBOURNE Technology
Author-email: engineering@finbourne.com
License: MIT
Keywords: OpenAPI,FINBOURNE,LUSID,Shrine API
Platform: UNKNOWN
Requires-Dist: six (>=1.10)
Requires-Dist: certifi (>=14.05.14)
Requires-Dist: python-dateutil (>=2.5.3)
Requires-Dist: urllib3 (>=1.15.1)
Requires-Dist: requests (>=2.21.0)
